eai/__init__.py
eai/eaichecker.py
eai/idn_services.py
idn_eai-1.0.0.dist-info/LICENSE.txt
idn_eai-1.0.0.dist-info/METADATA
idn_eai-1.0.0.dist-info/WHEEL
idn_eai-1.0.0.dist-info/top_level.txt
idn_eai-1.0.0.dist-info/RECORD
