Metadata-Version: 2.1
Name: idn-eai
Version: 1.0.0
Summary: Read the README file
Home-page: https://github.com/imarg3/idn-eai
Author: Arpit Gupta
Author-email: gupta.arpit03@gmail.com
License: MIT
Platform: UNKNOWN
Classifier: License :: OSI Approved :: MIT License
Classifier: Programming Language :: Python :: 3
Classifier: Programming Language :: Python :: 3.7
Classifier: Operating System :: OS Independent
Requires-Dist: dnspython
